[
  {
    "_id": "elonMusk1",
    "avatar": "spacex.png",
    "userName": "Elon Musk",
    "handle": "@elonmusk",
    "time": "23h",
    "title": "Amazing show about @inspiration4x mission!",
    "image": "grimes-karl-marx.jpg",
    "postTitle": "Countdown: Inspirational4 Mission to Space | Netflix Official Site",
    "description": "From training to launch to landing, this all-access docuseries rides along with the Inspiration4 crew on the first all-civilian orbital space ... netflix.com"
  },
  {
    "_id": "elonMusk1",
    "avatar": "spacex.png",
    "userName": "Elon Musk",
    "handle": "@elonmusk",
    "time": "23h",
    "title": "Amazing show about @inspiration4x mission!",
    "image": "grimes-karl-marx.jpg",
    "postTitle": "Countdown: Inspirational4 Mission to Space | Netflix Official Site",
    "description": "From training to launch to landing, this all-access docuseries rides along with the Inspiration4 crew on the first all-civilian orbital space ... netflix.com"
  }
]